Genclass/__init__.py
Genclass/genclass.py
Genclass-0.0.7.dist-info/METADATA
Genclass-0.0.7.dist-info/RECORD
Genclass-0.0.7.dist-info/WHEEL
Genclass-0.0.7.dist-info/top_level.txt
